aiotailf/__init__.py
aiotailf/cli.py
aiotailf-0.1.0.dist-info/LICENSE
aiotailf-0.1.0.dist-info/METADATA
aiotailf-0.1.0.dist-info/WHEEL
aiotailf-0.1.0.dist-info/entry_points.txt
aiotailf-0.1.0.dist-info/top_level.txt
aiotailf-0.1.0.dist-info/RECORD
